dp_tms/__init__.py
dp_tms/database/__init__.py
dp_tms/database/processing.py
dp_tms/database/storage.py
dp_tms/database/queries/__init__.py
dp_tms/database/queries/entities.py
dp_tms/database/queries/utils.py
dp_tms/scorers/__init__.py
dp_tms/scorers/distance.py
dp_tms/scorers/handlers.py
dp_tms/services/__init__.py
dp_tms/services/jarvis.py
dp_tms/utils/__init__.py
dp_tms/utils/athena.py
dp_tms-0.2.2.dist-info/METADATA
dp_tms-0.2.2.dist-info/WHEEL
dp_tms-0.2.2.dist-info/top_level.txt
dp_tms-0.2.2.dist-info/RECORD
