Metadata-Version: 2.1
Name: dp-tms
Version: 0.2.2
Summary: reusable utilities shared across tms
Home-page: UNKNOWN
Author: Ringier South Africa
Author-email: tools@ringier.co.za
License: UNKNOWN
Platform: UNKNOWN
Requires-Python: >=3.6
Requires-Dist: awswrangler (==2.14.0)
Requires-Dist: requests (==2.27.1)
Requires-Dist: scipy
Provides-Extra: develop
Requires-Dist: mpmath (==1.1.0) ; extra == 'develop'
Requires-Dist: regex (==2021.8.3) ; extra == 'develop'
Requires-Dist: requests (==2.27.1) ; extra == 'develop'
